blagbl/__init__.py
blagbl/tests/__init__.py
blagbl/tests/test_loading.py
blagbl/tools/__init__.py
blagbl/tools/main.py
blagbl-0.1.1.dist-info/METADATA
blagbl-0.1.1.dist-info/WHEEL
blagbl-0.1.1.dist-info/entry_points.txt
blagbl-0.1.1.dist-info/licenses/LICENSE
blagbl-0.1.1.dist-info/licenses/LICENSE.txt
blagbl-0.1.1.dist-info/RECORD
