Metadata-Version: 2.4
Name: blagbl
Version: 0.1.1
Summary: CLI tool for fetching and checking BLAG block list information.
Project-URL: Homepage, https://github.com/hardaker/blagbl
Author-email: Wes Hardaker <opensource@hardakers.net>
License: MIT License
License-File: LICENSE
License-File: LICENSE.txt
Classifier: Operating System :: OS Independent
Classifier: Programming Language :: Python :: 3
Requires-Python: >=3.7
Requires-Dist: dateparser
Requires-Dist: msgpack
Requires-Dist: pyfsdb
Requires-Dist: requests
Requires-Dist: rich
